mahlif/__init__.py
mahlif/__main__.py
mahlif/cli.py
mahlif/config.py
mahlif/encoding.py
mahlif/lilypond/__init__.py
mahlif/lilypond/converter.py
mahlif/models.py
mahlif/musicxml/__init__.py
mahlif/parser.py
mahlif/py.typed
mahlif/sibelius/MahlifExport.plg
mahlif/sibelius/README.md
mahlif/sibelius/__init__.py
mahlif/sibelius/__main__.py
mahlif/sibelius/automation/__init__.py
mahlif/sibelius/build.py
mahlif/sibelius/cli.py
mahlif/sibelius/convert.py
mahlif/sibelius/cyrus/Cyrus.plg
mahlif/sibelius/cyrus/README.md
mahlif/sibelius/manuscript/README.md
mahlif/sibelius/manuscript/__init__.py
mahlif/sibelius/manuscript/ast.py
mahlif/sibelius/manuscript/checker.py
mahlif/sibelius/manuscript/errors.py
mahlif/sibelius/manuscript/extract.py
mahlif/sibelius/manuscript/format.py
mahlif/sibelius/manuscript/lang.json
mahlif/sibelius/manuscript/lint.py
mahlif/sibelius/manuscript/lint_bodies.py
mahlif/sibelius/manuscript/lint_braces.py
mahlif/sibelius/manuscript/lint_common.py
mahlif/sibelius/manuscript/lint_directives.py
mahlif/sibelius/manuscript/lint_fix.py
mahlif/sibelius/manuscript/lint_methods.py
mahlif/sibelius/manuscript/lint_structure.py
mahlif/sibelius/manuscript/tokenizer.py
mahlif/sibelius/manuscript/tokens.py
mahlif/stats.py
mahlif-0.1.0.dist-info/licenses/LICENSE.md
mahlif-0.1.0.dist-info/WHEEL
mahlif-0.1.0.dist-info/entry_points.txt
mahlif-0.1.0.dist-info/METADATA
mahlif-0.1.0.dist-info/RECORD
