Metadata-Version: 2.4
Name: mahlif
Version: 0.1.0
Summary: Universal music notation interchange format with bidirectional converters
Keywords: music,notation,sibelius,lilypond,musicxml,converter
Author: Metaist LLC
Author-email: Metaist LLC <metaist@metaist.com>
License-Expression: MIT
License-File: LICENSE.md
Classifier: Development Status :: 4 - Beta
Classifier: Intended Audience :: Developers
Classifier: License :: OSI Approved :: MIT License
Classifier: Natural Language :: English
Classifier: Operating System :: OS Independent
Classifier: Programming Language :: Python
Classifier: Programming Language :: Python :: 3
Classifier: Programming Language :: Python :: 3 :: Only
Classifier: Programming Language :: Python :: 3.10
Classifier: Programming Language :: Python :: 3.11
Classifier: Programming Language :: Python :: 3.12
Classifier: Programming Language :: Python :: 3.13
Classifier: Programming Language :: Python :: 3.14
Classifier: Topic :: Software Development :: Libraries
Classifier: Typing :: Typed
Requires-Dist: rich>=13.0,<15.0
Requires-Dist: lxml>=5.0,<6.0
Requires-Python: >=3.10, <3.15
Project-URL: Homepage, https://github.com/metaist/mahlif
Project-URL: Documentation, https://metaist.github.io/mahlif/
Project-URL: Repository, https://github.com/metaist/mahlif.git
Project-URL: Changelog, https://github.com/metaist/mahlif/blob/main/CHANGELOG.md
